sqlIngestConfigs/__init__.py
sqlIngestConfigs-0.4.dist-info/LICENSE.txt
sqlIngestConfigs-0.4.dist-info/METADATA
sqlIngestConfigs-0.4.dist-info/WHEEL
sqlIngestConfigs-0.4.dist-info/top_level.txt
sqlIngestConfigs-0.4.dist-info/RECORD
