Metadata-Version: 2.1
Name: sqlIngestConfigs
Version: 0.4
Summary: Long description
Author: Data Platform
Author-email: heman@gamil.com
Classifier: Programming Language :: Python :: 3
Classifier: License :: OSI Approved :: MIT License
Classifier: Operating System :: OS Independent
License-File: LICENSE.txt
Requires-Dist: pyyaml
